{"api_result":1,"api_result_msg":"\u6210\u529f","api_data":{"api_dock_id":1,"api_ship_ke":[-1,1701,1615,1560,1622,1622,1526],"api_ship_lv":[-1,1,1,1,1,1,1],"api_nowhps":[-1,98,12,58,92,37,74,700,96,84,43,43,80],"api_maxhps":[-1,98,31,62,92,37,74,700,96,84,43,43,80],"api_midnight_flag":0,"api_eSlot":[[552,552,562,562,-1],[556,557,558,558,-1],[520,524,524,517,-1],[502,502,559,-1,-1],[502,502,559,-1,-1],[501,503,503,-1,-1]],"api_eKyouka":[[0,0,0,0],[0,0,0,0],[0,0,0,0],[0,0,0,0],[0,0,0,0],[0,0,0,0]],"api_fParam":[[102,0,90,92],[62,96,64,51],[87,48,90,88],[105,0,94,90],[58,56,114,52],[64,0,82,76]],"api_eParam":[[200,0,188,167],[25,0,50,80],[18,0,36,70],[58,88,44,36],[58,88,44,36],[15,0,0,35]],"api_search":[1,1],"api_formation":[3,3,1],"api_stage_flag":[1,1,1],"api_kouku":{"api_plane_from":[[3,6],[1,2,3]],"api_stage1":{"api_f_count":80,"api_f_lostcount":14,"api_e_count":376,"api_e_lostcount":119,"api_disp_seiku":0,"api_touch_plane":[-1,-1]},"api_stage2":{"api_f_count":13,"api_f_lostcount":0,"api_e_count":222,"api_e_lostcount":187,"api_air_fire":{"api_idx":4,"api_kind":1,"api_use_items":[122,122,106]}},"api_stage3":{"api_frai_flag":[-1,0,0,0,0,0,0],"api_erai_flag":[-1,0,0,0,0,0,0],"api_fbak_flag":[-1,0,0,0,1,0,0],"api_ebak_flag":[-1,0,0,0,0,0,0],"api_fcl_flag":[-1,0,0,0,0,0,0],"api_ecl_flag":[-1,0,0,0,0,0,0],"api_fdam":[-1,0,0,0,0,0,0],"api_edam":[-1,0,0,0,0,0,0]}}}}